odoo/addons/sale_line_refund_to_invoice_qty_skip_anglo_saxon/README.rst
odoo/addons/sale_line_refund_to_invoice_qty_skip_anglo_saxon/__init__.py
odoo/addons/sale_line_refund_to_invoice_qty_skip_anglo_saxon/__manifest__.py
odoo/addons/sale_line_refund_to_invoice_qty_skip_anglo_saxon/i18n/es.po
odoo/addons/sale_line_refund_to_invoice_qty_skip_anglo_saxon/i18n/it.po
odoo/addons/sale_line_refund_to_invoice_qty_skip_anglo_saxon/i18n/sale_line_refund_to_invoice_qty_skip_anglo_saxon.pot
odoo/addons/sale_line_refund_to_invoice_qty_skip_anglo_saxon/readme/CONTRIBUTORS.rst
odoo/addons/sale_line_refund_to_invoice_qty_skip_anglo_saxon/readme/DESCRIPTION.rst
odoo/addons/sale_line_refund_to_invoice_qty_skip_anglo_saxon/static/description/icon.png
odoo/addons/sale_line_refund_to_invoice_qty_skip_anglo_saxon/static/description/index.html
odoo/addons/sale_line_refund_to_invoice_qty_skip_anglo_saxon/tests/__init__.py
odoo/addons/sale_line_refund_to_invoice_qty_skip_anglo_saxon/tests/test_sale_line_refund_to_invoice_qty_skip_anglo_saxon.py
odoo/addons/sale_line_refund_to_invoice_qty_skip_anglo_saxon/wizard/__init__.py
odoo/addons/sale_line_refund_to_invoice_qty_skip_anglo_saxon/wizard/account_move_reversal.py
odoo/addons/sale_line_refund_to_invoice_qty_skip_anglo_saxon/wizard/account_move_reversal_view.xml
odoo14_addon_sale_line_refund_to_invoice_qty_skip_anglo_saxon-14.0.1.0.1.dev7.dist-info/METADATA
odoo14_addon_sale_line_refund_to_invoice_qty_skip_anglo_saxon-14.0.1.0.1.dev7.dist-info/WHEEL
odoo14_addon_sale_line_refund_to_invoice_qty_skip_anglo_saxon-14.0.1.0.1.dev7.dist-info/top_level.txt
odoo14_addon_sale_line_refund_to_invoice_qty_skip_anglo_saxon-14.0.1.0.1.dev7.dist-info/RECORD
