Metadata-Version: 2.1
Name: odoo14-addon-sale_line_refund_to_invoice_qty_skip_anglo_saxon
Version: 14.0.1.0.1.dev7
Summary: Sale Line Refund To Invoice Qty skip anglo saxon.
Home-page: https://github.com/OCA/account-invoicing
Author: ForgeFlow S.L, Odoo Community Association (OCA)
Author-email: support@odoo-community.org
License: AGPL-3
Classifier: Programming Language :: Python
Classifier: Framework :: Odoo
Classifier: Framework :: Odoo :: 14.0
Classifier: License :: OSI Approved :: GNU Affero General Public License v3
Classifier: Development Status :: 4 - Beta
Requires-Python: >=3.6
Requires-Dist: odoo14-addon-account-invoice-refund-reason-skip-anglo-saxon
Requires-Dist: odoo14-addon-sale-line-refund-to-invoice-qty
Requires-Dist: odoo<14.1dev,>=14.0a
